{
  "main": {
    "id": "d1e6d20a9993ea98",
    "type": "split",
    "children": [
      {
        "id": "834b7b60ccc30235",
        "type": "tabs",
        "children": [
          {
            "id": "4cb230ed8d9652db",
            "type": "leaf",
            "state": {
              "type": "bases",
              "state": {
                "file": "索引.base",
                "viewName": "表格"
              },
              "icon": "lucide-table",
              "title": "索引"
            }
          }
        ]
      }
    ],
    "direction": "vertical"
  },
  "left": {
    "id": "462bb8bcb24311c3",
    "type": "split",
    "children": [
      {
        "id": "1d97b6d5096431da",
        "type": "tabs",
        "children": [
          {
            "id": "ed2fddd10e618346",
            "type": "leaf",
            "state": {
              "type": "file-explorer",
              "state": {
                "sortOrder": "alphabetical",
                "autoReveal": false
              },
              "icon": "lucide-folder-closed",
              "title": "文件列表"
            }
          },
          {
            "id": "7059299b1e347843",
            "type": "leaf",
            "state": {
              "type": "search",
              "state": {
                "query": "",
                "matchingCase": false,
                "explainSearch": false,
                "collapseAll": false,
                "extraContext": false,
                "sortOrder": "alphabetical"
              },
              "icon": "lucide-search",
              "title": "搜索"
            }
          },
          {
            "id": "368ab7725281a1a4",
            "type": "leaf",
            "state": {
              "type": "bookmarks",
              "state": {},
              "icon": "lucide-bookmark",
              "title": "书签"
            }
          }
        ]
      }
    ],
    "direction": "horizontal",
    "width": 200
  },
  "right": {
    "id": "e3f998aeec958431",
    "type": "split",
    "children": [
      {
        "id": "457930e27d0d2740",
        "type": "tabs",
        "children": [
          {
            "id": "77377b64369c0d77",
            "type": "leaf",
            "state": {
              "type": "backlink",
              "state": {
                "collapseAll": false,
                "extraContext": false,
                "sortOrder": "alphabetical",
                "showSearch": false,
                "searchQuery": "",
                "backlinkCollapsed": false,
                "unlinkedCollapsed": false
              },
              "icon": "links-coming-in",
              "title": "反向链接"
            }
          },
          {
            "id": "d6481fa920a0c6df",
            "type": "leaf",
            "state": {
              "type": "outgoing-link",
              "state": {
                "file": "索引.base",
                "linksCollapsed": true,
                "unlinkedCollapsed": true
              },
              "icon": "links-going-out",
              "title": "索引 的出链列表"
            }
          },
          {
            "id": "40062a9c407094b4",
            "type": "leaf",
            "state": {
              "type": "tag",
              "state": {
                "sortOrder": "frequency",
                "useHierarchy": true
              },
              "icon": "lucide-tags",
              "title": "标签"
            }
          },
          {
            "id": "21fc951e1358c183",
            "type": "leaf",
            "state": {
              "type": "outline",
              "state": {
                "file": "索引.base",
                "followCursor": false,
                "showSearch": false,
                "searchQuery": ""
              },
              "icon": "lucide-list",
              "title": "索引 的大纲"
            }
          },
          {
            "id": "0ccb64fcd5acc7bf",
            "type": "leaf",
            "state": {
              "type": "git-view",
              "state": {},
              "icon": "git-pull-request",
              "title": "Source Control"
            }
          }
        ],
        "currentTab": 4
      }
    ],
    "direction": "horizontal",
    "width": 342.5
  },
  "left-ribbon": {
    "hiddenItems": {
      "bases:创建新数据库": false,
      "switcher:打开快速切换": false,
      "graph:查看关系图谱": false,
      "canvas:新建白板": false,
      "daily-notes:打开/创建今天的日记": false,
      "templates:插入模板": false,
      "command-palette:打开命令面板": false
    }
  },
  "active": "ed2fddd10e618346",
  "lastOpenFiles": [
    "未命名 1.base",
    "索引.base",
    "未命名 2.base",
    "未命名 4.base",
    "定位测量仪设备终端通信协议.md",
    "未命名 3.base",
    "git/设置ssh 证书登陆.md",
    "git/导入自定义证书解决 git 仓库https访问时的证书验证失败.md",
    "android/ffmpeg.md",
    "git/修改git远程仓库地址.md",
    "git",
    "GGA 报文解析以及坐标系转换参考.md",
    "GNSS 北斗星基增强定位测量仪 设备终端通信协议 草稿.md",
    "使用 Python Kivy 搭建移动端开发环境.md",
    "如何在 ubuntu20.04 amd64 上搭建 arm64 交叉编译环境.md",
    "高光谱相机数据处理与应用开发C++高级程序员招聘需求.md",
    "QML Material 主题颜色的修改.md",
    "gitlab 新地址访问方法.md",
    "Qt/Qt 6 On Ubuntu22.04.md",
    "midwayjs/React Router.md",
    "midwayjs/Passport.md",
    "midwayjs/MySql.md",
    "midwayjs/MongoDB.md",
    "math/LinearAlgebra.md",
    "linux/Ubuntu 指令杂记.md",
    "RTK手薄中，点测量，点放样以及线放样等功能的操作以及作用.md",
    "lidar/Livox Horizon.md",
    "android/Android Studio On Linux.md",
    "智能装备研发团队人员配置方案.md",
    "vcpkg 构建交叉编译环境",
    "cheetah/orb_slam3.md",
    "cheetah/MIT_cheetah Notes.md",
    "dot_product.svg",
    "Diagram2.svg",
    "Diagram1.svg",
    "Diagram.svg",
    "QT_QML_GENERATE_QMLLS_INI.png",
    "lidar",
    "android",
    "Qt",
    "未命名.canvas"
  ]
}